CHANGES
LICENSE
MANIFEST.in
README.rst
setup.py
bin/py-mysql2pgsql
docs/Makefile
docs/changes.rst
docs/conf.py
docs/index.rst
docs/make.bat
docs/_build/doctrees/changes.doctree
docs/_build/doctrees/environment.pickle
docs/_build/doctrees/index.doctree
docs/_build/doctrees/api/index.doctree
docs/_build/doctrees/api/mysql2pgsql/index.doctree
docs/_build/doctrees/api/mysql2pgsql/mysql_reader.doctree
docs/_build/doctrees/api/mysql2pgsql/postgres_db_writer.doctree
docs/_build/doctrees/api/mysql2pgsql/postgres_file_writer.doctree
docs/_build/doctrees/api/mysql2pgsql/postgres_writer.doctree
docs/_build/html/.buildinfo
docs/_build/html/changes.html
docs/_build/html/genindex.html
docs/_build/html/index.html
docs/_build/html/objects.inv
docs/_build/html/py-modindex.html
docs/_build/html/search.html
docs/_build/html/searchindex.js
docs/_build/html/_sources/changes.txt
docs/_build/html/_sources/index.txt
docs/_build/html/_sources/api/index.txt
docs/_build/html/_sources/api/mysql2pgsql/index.txt
docs/_build/html/_sources/api/mysql2pgsql/mysql_reader.txt
docs/_build/html/_sources/api/mysql2pgsql/postgres_db_writer.txt
docs/_build/html/_sources/api/mysql2pgsql/postgres_file_writer.txt
docs/_build/html/_sources/api/mysql2pgsql/postgres_writer.txt
docs/_build/html/_static/basic.css
docs/_build/html/_static/default.css
docs/_build/html/_static/doctools.js
docs/_build/html/_static/file.png
docs/_build/html/_static/jquery.js
docs/_build/html/_static/minus.png
docs/_build/html/_static/plus.png
docs/_build/html/_static/pygments.css
docs/_build/html/_static/searchtools.js
docs/_build/html/_static/sidebar.js
docs/_build/html/_static/underscore.js
docs/_build/html/api/index.html
docs/_build/html/api/mysql2pgsql/index.html
docs/_build/html/api/mysql2pgsql/mysql_reader.html
docs/_build/html/api/mysql2pgsql/postgres_db_writer.html
docs/_build/html/api/mysql2pgsql/postgres_file_writer.html
docs/_build/html/api/mysql2pgsql/postgres_writer.html
docs/api/index.rst
docs/api/mysql2pgsql/index.rst
py_mysql2pgsql.egg-info/PKG-INFO
py_mysql2pgsql.egg-info/SOURCES.txt
py_mysql2pgsql.egg-info/dependency_links.txt
py_mysql2pgsql.egg-info/not-zip-safe
py_mysql2pgsql.egg-info/requires.txt
py_mysql2pgsql.egg-info/top_level.txt
