Metadata-Version: 1.0
Name: py-mysql2pgsql
Version: 0.1.2
Summary: Tool for migrating/converting from mysql to postgresql.
Home-page: https://github.com/philipsoutham/py-mysql2pgsql
Author: Philip Southam
Author-email: philipsoutham@gmail.com
License: MIT License
Keywords: mysql postgres postgresql pgsql psql migration
Platform: any
Classifier: License :: OSI Approved :: MIT License
Classifier: Development Status :: 3 - Alpha
Classifier: Environment :: Console
Classifier: Intended Audience :: System Administrators
Classifier: Intended Audience :: Developers
Classifier: Natural Language :: English
Classifier: Operating System :: OS Independent
Classifier: Programming Language :: Python :: 2.6
Classifier: Programming Language :: Python :: 2.7
Classifier: Topic :: Database
Classifier: Topic :: Utilities
